[
    {
        "title": "Corwin Convertible Sleeper",
        "price": 316.99,
        "color": 1,
        "imageUrl": "https://secure.img1-fg.wfcdn.com/im/80898831/resize-h160-w160%5Ecompr-r85/9433/94334845/Corwin+Convertible+Sleeper.jpg",
        "subDepartmentItem": "6025d70c4481270d383ebcc3"   
    },
    {
        "title": "Nickles Velvet 52.36\" Armless Loveseat",
        "price": 639.99,
        "color": 3,
        "imageUrl": "https://secure.img1-fg.wfcdn.com/im/53242697/resize-h160-w160%5Ecompr-r85/9927/99276238/Nickles+Velvet+52.36%2522+Armless+Loveseat.jpg",
        "subDepartmentItem": "6025d70c4481270d383ebcc3"   
    },
    {
        "title": "Lewellen Velvet 71.6\" Square Arm Sofa",
        "price": 469.99,
        "color": 10,
        "imageUrl": "https://secure.img1-fg.wfcdn.com/im/66086890/resize-h160-w160%5Ecompr-r85/1083/108360870/Lewellen+Velvet+71.6%2522+Square+Arm+Sofa.jpg",
        "subDepartmentItem": "6025d70c4481270d383ebcc3"   
    },
    {
        "title": "Quinones Chesterfield 54\" Rolled Arms Loveseat",
        "price": 559.99,
        "color": 8,
        "imageUrl": "https://secure.img1-fg.wfcdn.com/im/24368033/resize-h160-w160%5Ecompr-r85/8264/82649252/Quinones+Chesterfield+54%2527%2527+Rolled+Arms+Loveseat.jpg",
        "subDepartmentItem": "6025d70c4481270d383ebcc3"
    },
    {
        "title": "Lewellen Velvet 58\" Square Arm Loveseat",
        "price": 409.99,
        "color": 9,
        "imageUrl": "https://secure.img1-fg.wfcdn.com/im/21135897/resize-h160-w160%5Ecompr-r85/1083/108360554/Lewellen+Velvet+58%2522+Square+Arm+Loveseat.jpg",
        "subDepartmentItem": "6025d70c4481270d383ebcc3"
    },
    {
        "title": "Ibiza Microfiber 80.3\" Flared Arm Sofa",
        "price": 599.99,
        "color": 2,
        "imageUrl": "https://secure.img1-fg.wfcdn.com/im/79862867/resize-h160-w160%5Ecompr-r85/7881/78812972/Ibiza+Microfiber+80.3%2522+Flared+Arm+Sofa.jpg",
        "subDepartmentItem": "6025d70c4481270d383ebcc3"
    },
    {
        "title": "Minter 89\" Pillow Top Arm Sofa Bed",
        "price": 609.99,
        "color": 6,
        "imageUrl": "https://secure.img1-fg.wfcdn.com/im/64481832/resize-h160-w160%5Ecompr-r85/1079/107976340/Minter+89%2522+Pillow+Top+Arm+Sofa+Bed.jpg",
        "subDepartmentItem": "6025d70c4481270d383ebcc3"
    },
    {
        "title": "Banton Standard 52.36\" Armless Loveseat",
        "price": 649.99,
        "color": 3,
        "imageUrl": "https://secure.img1-fg.wfcdn.com/im/06690162/resize-h160-w160%5Ecompr-r85/9926/99269688/Banton+Standard++52.36%2522+Armless+Loveseat.jpg",
        "subDepartmentItem": "6025d70c4481270d383ebcc3"
    },
    {
        "title": "Ibiza Loveseat",
        "price": 399.99,
        "color": 2,
        "imageUrl": "https://secure.img1-fg.wfcdn.com/im/19044240/resize-h160-w160%5Ecompr-r85/7910/79102176/Ibiza+Loveseat.jpg",
        "subDepartmentItem": "6025d70c4481270d383ebcc3"
    },
    {
        "title": "Nia Velvet 81.5\" Square Arm Sleeper",
        "price": 739.99,
        "color": 7,
        "imageUrl": "https://secure.img1-fg.wfcdn.com/im/06970566/resize-h160-w160%5Ecompr-r85/6008/60088906/Nia+Velvet+81.5%2522+Square+Arm+Sleeper.jpg",
        "subDepartmentItem": "6025d70c4481270d383ebcc3"
    },
    {
        "title": "Isaacs 112\" Left Hand Facing Sectional",
        "price": 1499.99,
        "color": 2,
        "imageUrl": "https://secure.img1-fg.wfcdn.com/im/82390747/resize-h160-w160%5Ecompr-r85/4382/43827453/Isaacs+112%2522+Left+Hand+Facing+Sectional.jpg",
        "subDepartmentItem": "6025d70c4481270d383ebcc4"
    },
    {
        "title": "Kayden 84\" Chenille Reversible Sleeper Sofa & Chaise",
        "price": 1199.99,
        "color": 5,
        "imageUrl": "https://secure.img1-fg.wfcdn.com/im/68175606/resize-h160-w160%5Ecompr-r85/4866/48667514/Kayden+84%2522+Chenille+Reversible+Sleeper+Sofa+%2526+Chaise.jpg",
        "subDepartmentItem": "6025d70c4481270d383ebcc4"
    },
    {
        "title": "Baldy 90\" Right Hand Facing Sofa & Chaise",
        "price": 1219.99,
        "color": 5,
        "imageUrl": "https://secure.img1-fg.wfcdn.com/im/98318801/resize-h160-w160%5Ecompr-r85/1142/114246217/Baldy+90%2522+Right+Hand+Facing+Sofa+%2526+Chaise.jpg",
        "subDepartmentItem": "6025d70c4481270d383ebcc4"
    },
    {
        "title": "Hendrick 88.6\" Pull Out Reversible Sleeper Sectional",
        "price": 1279.99,
        "color": 1,
        "imageUrl": "https://secure.img1-fg.wfcdn.com/im/18194670/resize-h160-w160%5Ecompr-r85/8001/80013810/Hendrick+88.6%2522+Pull+Out+Reversible+Sleeper+Sectional.jpg",
        "subDepartmentItem": "6025d70c4481270d383ebcc4"
    },
    {
        "title": "Althea 134\" Left Hand Facing Modular Sectional",
        "price": 1769.99,
        "color": 1,
        "imageUrl": "https://secure.img1-fg.wfcdn.com/im/43902319/resize-h160-w160%5Ecompr-r85/4725/47255483/Althea+134%2522+Left+Hand+Facing+Modular+Sectional.jpg",
        "subDepartmentItem": "6025d70c4481270d383ebcc4"
    },
    {
        "title": "Galena Left Hand Facing Sectional",
        "price": 1459.99,
        "color": 2,
        "imageUrl": "https://secure.img1-fg.wfcdn.com/im/75572569/resize-h160-w160%5Ecompr-r85/3188/31885382/Galena+Left+Hand+Facing+Sectional.jpg",
        "subDepartmentItem": "6025d70c4481270d383ebcc4"
    },
    {
        "title": "150\" Left Hand Facing Large Sectional",
        "price": 2579.99,
        "color": 2,
        "imageUrl": "https://secure.img1-fg.wfcdn.com/im/21558680/resize-h160-w160%5Ecompr-r85/6161/61612740/150%2522+Left+Hand+Facing+Large+Sectional.jpg",
        "subDepartmentItem": "6025d70c4481270d383ebcc4"
    },
    {
        "title": "Gerrald 124\" Sectional",
        "price": 2129.99,
        "color": 18,
        "imageUrl": "https://secure.img1-fg.wfcdn.com/im/02271809/resize-h160-w160%5Ecompr-r85/1137/113769173/Gerrald+124%2522+Sectional.jpg",
        "subDepartmentItem": "6025d70c4481270d383ebcc4"
    },
    {
        "title": "Perrault 130\" Right Hand Facing Sectional",
        "price": 1699.99,
        "color": 1,
        "imageUrl": "https://secure.img1-fg.wfcdn.com/im/45021869/resize-h160-w160%5Ecompr-r85/4960/49600283/Perrault+130%2522+Right+Hand+Facing+Sectional.jpg",
        "subDepartmentItem": "6025d70c4481270d383ebcc4"
    },
    {
        "title": "Russ 103.5\" Sectional",
        "price": 1169.99,
        "color": 11,
        "imageUrl": "https://secure.img1-fg.wfcdn.com/im/95138831/resize-h160-w160%5Ecompr-r85/1095/109557982/Russ+103.5%2522+Sectional+with+Ottoman.jpg",
        "subDepartmentItem": "6025d70c4481270d383ebcc4"
    }
]